sesh/Dockerfile
sesh/__init__.py
sesh/_version.py
sesh/exceptions.py
sesh/py.typed
sesh/backend/__init__.py
sesh/backend/base.py
sesh/backend/memmap.py
sesh/backend/redis.py
sesh/dependencies/__init__.py
sesh/dependencies/authentication.py
sesh/models/__init__.py
sesh/models/cookie.py
sesh/models/key.py
sesh/session/__init__.py
sesh/session/base.py
sesh/session/cookie.py
Sesh-0.7.2.dist-info/LICENSE
Sesh-0.7.2.dist-info/METADATA
Sesh-0.7.2.dist-info/WHEEL
Sesh-0.7.2.dist-info/top_level.txt
Sesh-0.7.2.dist-info/RECORD
